aiddit/__init__.py
aiddit/utils.py
aiddit/comprehension/__init__.py
aiddit/comprehension/comprehension_export_feishu.py
aiddit/comprehension/comprehension_result_export_feishu.py
aiddit/comprehension/comprehension_xuanti.py
aiddit/comprehension/comprehension_xuanti_pins_search.py
aiddit/comprehension/coomprehension_xuanti_test.py
aiddit/comprehension/key_point/__init__.py
aiddit/comprehension/key_point/batch_inference_key_point.py
aiddit/comprehension/key_point/comprehension_export_feishu.py
aiddit/comprehension/key_point/comprehension_key_point.py
aiddit/comprehension/key_point/comprehension_key_point_test.py
aiddit/comprehension/renshe/__init__.py
aiddit/comprehension/renshe/comprehension_renshe_export_feishu.py
aiddit/comprehension/renshe/note_script_prompt.py
aiddit/comprehension/renshe/renshe_history_note_data_extract.py
aiddit/comprehension/renshe/renshe_json_format.py
aiddit/comprehension/renshe/renshe_materials_summary.py
aiddit/comprehension/renshe/renshe_pipeline.py
aiddit/comprehension/renshe/renshe_prompt_0111.py
aiddit/comprehension/renshe/renshe_script_export_feishu.py
aiddit/comprehension/renshe/renshe_summary_0111.py
aiddit/comprehension/renshe/renshe_summary_0214.py
aiddit/comprehension/renshe/renshe_summary_0218.py
aiddit/comprehension/renshe/renshe_summary_prompt_0214.py
aiddit/comprehension/renshe/renshe_summary_prompt_0218.py
aiddit/comprehension/renshe_video/__init__.py
aiddit/comprehension/renshe_video/account_note_data_fetch.py
aiddit/comprehension/renshe_video/video_comprehension.py
aiddit/comprehension/renshe_video/video_renshe_build.py
aiddit/comprehension/script0221/__init__.py
aiddit/comprehension/script0221/script_compehension.py
aiddit/comprehension/script0221/script_prompt.py
aiddit/create/__init__.py
aiddit/create/create_script.py
aiddit/create/create_script_export_feishu.py
aiddit/create/create_xuanti_0113.py
aiddit/create/create_xuanti_0218.py
aiddit/create/create_xuanti_search.py
aiddit_agic_core-0.1.6.dist-info/METADATA
aiddit_agic_core-0.1.6.dist-info/WHEEL
aiddit_agic_core-0.1.6.dist-info/top_level.txt
aiddit_agic_core-0.1.6.dist-info/RECORD
