Metadata-Version: 2.1
Name: aiddit_agic_core
Version: 0.1.6
Summary: aiddit agic core
Home-page: https://www.aiddit.com
Author: nieqi
Author-email: burningpush@gmail.com
Classifier: Programming Language :: Python :: 3
Classifier: License :: OSI Approved :: MIT License
Classifier: Operating System :: OS Independent
Requires-Python: >=3.10
Requires-Dist: aiohappyeyeballs==2.4.4
Requires-Dist: aiohttp==3.11.9
Requires-Dist: aiosignal==1.3.1
Requires-Dist: annotated-types==0.7.0
Requires-Dist: anthropic==0.42.0
Requires-Dist: anyio==4.6.2.post1
Requires-Dist: async-timeout==5.0.1
Requires-Dist: attrs==24.2.0
Requires-Dist: backports.tarfile==1.2.0
Requires-Dist: cachetools==5.5.0
Requires-Dist: certifi==2025.1.31
Requires-Dist: cffi==1.17.1
Requires-Dist: charset-normalizer==3.4.0
Requires-Dist: cryptography==43.0.3
Requires-Dist: curl-cffi==0.7.4
Requires-Dist: dashtext==0.0.7
Requires-Dist: decorator==5.1.1
Requires-Dist: distro==1.9.0
Requires-Dist: docstring-parser==0.16
Requires-Dist: docutils==0.21.2
Requires-Dist: exceptiongroup==1.2.2
Requires-Dist: ffmpeg-python==0.2.0
Requires-Dist: frozenlist==1.5.0
Requires-Dist: future==1.0.0
Requires-Dist: google-ai-generativelanguage==0.6.15
Requires-Dist: google-api-core==2.24.0
Requires-Dist: google-api-python-client==2.155.0
Requires-Dist: google-auth==2.37.0
Requires-Dist: google-auth-httplib2==0.2.0
Requires-Dist: google-cloud-aiplatform==1.75.0
Requires-Dist: google-cloud-bigquery==3.27.0
Requires-Dist: google-cloud-core==2.4.1
Requires-Dist: google-cloud-resource-manager==1.14.0
Requires-Dist: google-cloud-storage==2.19.0
Requires-Dist: google-crc32c==1.6.0
Requires-Dist: google-genai==1.2.0
Requires-Dist: google-generativeai==0.8.4
Requires-Dist: google-resumable-media==2.7.2
Requires-Dist: googleapis-common-protos==1.66.0
Requires-Dist: grpc-google-iam-v1==0.13.1
Requires-Dist: grpcio==1.71.0
Requires-Dist: grpcio-status==1.68.1
Requires-Dist: h11==0.14.0
Requires-Dist: httpcore==1.0.7
Requires-Dist: httplib2==0.22.0
Requires-Dist: httpx==0.28.0
Requires-Dist: id==1.5.0
Requires-Dist: idna==3.10
Requires-Dist: imageio==2.37.0
Requires-Dist: imageio-ffmpeg==0.6.0
Requires-Dist: importlib-metadata==8.5.0
Requires-Dist: jaraco.classes==3.4.0
Requires-Dist: jaraco.context==6.0.1
Requires-Dist: jaraco.functools==4.1.0
Requires-Dist: jiter==0.8.0
Requires-Dist: keyring==25.6.0
Requires-Dist: markdown-it-py==3.0.0
Requires-Dist: mdurl==0.1.2
Requires-Dist: milvus-lite==2.4.11
Requires-Dist: mmh3==5.0.1
Requires-Dist: more-itertools==10.6.0
Requires-Dist: multidict==6.1.0
Requires-Dist: nh3==0.2.21
Requires-Dist: numpy==2.1.3
Requires-Dist: openai==1.61.1
Requires-Dist: packaging==24.2
Requires-Dist: pandas==2.2.3
Requires-Dist: pillow==10.4.0
Requires-Dist: proglog==0.1.10
Requires-Dist: propcache==0.2.1
Requires-Dist: proto-plus==1.25.0
Requires-Dist: protobuf==5.29.1
Requires-Dist: pyasn1==0.6.1
Requires-Dist: pyasn1-modules==0.4.1
Requires-Dist: pycparser==2.22
Requires-Dist: pydantic==2.10.2
Requires-Dist: pydantic-core==2.27.1
Requires-Dist: PyExecJS==1.5.1
Requires-Dist: Pygments==2.19.1
Requires-Dist: pyparsing==3.2.0
Requires-Dist: python-dateutil==2.9.0.post0
Requires-Dist: python-dotenv==1.0.1
Requires-Dist: pytz==2024.2
Requires-Dist: readme-renderer==44.0
Requires-Dist: requests==2.32.3
Requires-Dist: requests-toolbelt==1.0.0
Requires-Dist: rfc3986==2.0.0
Requires-Dist: rich==13.9.4
Requires-Dist: rsa==4.9
Requires-Dist: setproctitle==1.3.5
Requires-Dist: shapely==2.0.6
Requires-Dist: six==1.17.0
Requires-Dist: sniffio==1.3.1
Requires-Dist: socksio==1.0.0
Requires-Dist: sseclient-py==1.8.0
Requires-Dist: tenacity==9.0.0
Requires-Dist: tqdm==4.67.1
Requires-Dist: twine==6.1.0
Requires-Dist: typing-extensions==4.12.2
Requires-Dist: tzdata==2024.2
Requires-Dist: ujson==5.10.0
Requires-Dist: uritemplate==4.1.1
Requires-Dist: urllib3==2.2.3
Requires-Dist: volcengine-python-sdk==1.0.123
Requires-Dist: websockets==14.2
Requires-Dist: yarl==1.18.3
Requires-Dist: zipp==3.21.0
